supabase_overleaf/__init__.py
supabase_overleaf/crawler_detail.py
supabase_overleaf/crawler_general.py
supabase_overleaf/db_handler.py
supabase_overleaf/main.py
supabase_overleaf/config/__init__.py
supabase_overleaf/config/config.py
supabase_overleaf-0.1.1.dist-info/LICENSE
supabase_overleaf-0.1.1.dist-info/METADATA
supabase_overleaf-0.1.1.dist-info/WHEEL
supabase_overleaf-0.1.1.dist-info/entry_points.txt
supabase_overleaf-0.1.1.dist-info/top_level.txt
supabase_overleaf-0.1.1.dist-info/RECORD
