Metadata-Version: 2.1
Name: supabase-overleaf
Version: 0.1.1
Summary: A tool to crawl Overleaf templates and store data in Supabase
Home-page: https://github.com/chenxingqiang/supabase-overleaf-crawler
Author: Chen, Xingqiang
Author-email: chen.xinqiang@iechor.com
Classifier: Development Status :: 3 - Alpha
Classifier: Intended Audience :: Developers
Classifier: License :: OSI Approved :: MIT License
Classifier: Operating System :: OS Independent
Classifier: Programming Language :: Python :: 3
Classifier: Programming Language :: Python :: 3.7
Classifier: Programming Language :: Python :: 3.8
Classifier: Programming Language :: Python :: 3.9
Classifier: Programming Language :: Python :: 3.10
Classifier: Programming Language :: Python :: 3.11
Requires-Python: >=3.7
License-File: LICENSE
Requires-Dist: requests
Requires-Dist: beautifulsoup4
Requires-Dist: supabase
